dagster_aws/__init__.py
dagster_aws/py.typed
dagster_aws/version.py
dagster_aws/athena/__init__.py
dagster_aws/athena/resources.py
dagster_aws/cloudwatch/__init__.py
dagster_aws/cloudwatch/loggers.py
dagster_aws/ecr/__init__.py
dagster_aws/ecr/resources.py
dagster_aws/ecs/__init__.py
dagster_aws/ecs/container_context.py
dagster_aws/ecs/launcher.py
dagster_aws/ecs/tasks.py
dagster_aws/ecs/test_utils.py
dagster_aws/ecs/utils.py
dagster_aws/emr/__init__.py
dagster_aws/emr/configs.py
dagster_aws/emr/configs_spark.py
dagster_aws/emr/emr.py
dagster_aws/emr/emr_step_main.py
dagster_aws/emr/main.py.template
dagster_aws/emr/pyspark_step_launcher.py
dagster_aws/emr/types.py
dagster_aws/emr/utils.py
dagster_aws/redshift/__init__.py
dagster_aws/redshift/resources.py
dagster_aws/s3/__init__.py
dagster_aws/s3/compute_log_manager.py
dagster_aws/s3/file_manager.py
dagster_aws/s3/io_manager.py
dagster_aws/s3/ops.py
dagster_aws/s3/resources.py
dagster_aws/s3/s3_fake_resource.py
dagster_aws/s3/sensor.py
dagster_aws/s3/solids.py
dagster_aws/s3/utils.py
dagster_aws/secretsmanager/__init__.py
dagster_aws/secretsmanager/resources.py
dagster_aws/secretsmanager/secrets.py
dagster_aws/utils/__init__.py
dagster_aws/utils/mrjob/__init__.py
dagster_aws/utils/mrjob/log4j.py
dagster_aws/utils/mrjob/retry.py
dagster_aws/utils/mrjob/utils.py
dagster_aws-1.0.5.dist-info/LICENSE
dagster_aws-1.0.5.dist-info/METADATA
dagster_aws-1.0.5.dist-info/WHEEL
dagster_aws-1.0.5.dist-info/top_level.txt
dagster_aws-1.0.5.dist-info/RECORD
