Metadata-Version: 2.1
Name: dagster-aws
Version: 1.0.5
Summary: Package for AWS-specific Dagster framework solid and resource components.
Home-page: https://github.com/dagster-io/dagster/tree/master/python_modules/libraries/dagster-aws
Author: Elementl
Author-email: hello@elementl.com
License: Apache-2.0
Platform: UNKNOWN
Classifier: Programming Language :: Python :: 3.7
Classifier: Programming Language :: Python :: 3.8
Classifier: Programming Language :: Python :: 3.9
Classifier: Programming Language :: Python :: 3.10
Classifier: License :: OSI Approved :: Apache Software License
Classifier: Operating System :: OS Independent
License-File: LICENSE
Requires-Dist: boto3
Requires-Dist: dagster (==1.0.5)
Requires-Dist: packaging
Requires-Dist: requests
Provides-Extra: pyspark
Requires-Dist: dagster-pyspark ; extra == 'pyspark'
Provides-Extra: redshift
Requires-Dist: psycopg2-binary ; extra == 'redshift'
Provides-Extra: test
Requires-Dist: moto (>=2.2.8) ; extra == 'test'
Requires-Dist: requests-mock ; extra == 'test'
Requires-Dist: xmltodict (==0.12.0) ; extra == 'test'
